testpackage12121/__init__.py
testpackage12121/chunk_it.py
testpackage12121/clean_it.py
testpackage12121/extractor.py
testpackage12121/get_evaluation_question.py
testpackage12121/prag.py
testpackage12121/trulens.py
testpackage12121/utils.py
testpackage12121-0.0.1.dist-info/LICENSE
testpackage12121-0.0.1.dist-info/METADATA
testpackage12121-0.0.1.dist-info/WHEEL
testpackage12121-0.0.1.dist-info/top_level.txt
testpackage12121-0.0.1.dist-info/RECORD
