Metadata-Version: 2.1
Name: testpackage12121
Version: 0.0.1
Summary: This library is to search the best parameters across different steps of the RAG process.
Home-page: https://github.com/hidevscommunity/gen-ai-library/tree/main/Ankit
Author: deepakchawla1307
Author-email: deepakchawla35@gmail.com
License: MIT
Classifier: License :: OSI Approved :: MIT License
Classifier: Programming Language :: Python :: 3
Classifier: Programming Language :: Python :: 3.6
Classifier: Programming Language :: Python :: 3.7
Classifier: Programming Language :: Python :: 3.8
Classifier: Programming Language :: Python :: 3.9
Classifier: Programming Language :: Python :: 3.10
License-File: LICENSE
Requires-Dist: langchain >=0.1.13
Requires-Dist: langchain-community >=0.0.29
Requires-Dist: langchain-core >=0.1.36
Requires-Dist: langchain-openai >=0.1.1
Requires-Dist: langchain-text-splitters >=0.0.1
Requires-Dist: tiktoken >=0.6.0
Requires-Dist: scikit-learn >=1.4.1.post1
Requires-Dist: trulens-eval >=0.27.0
Requires-Dist: chromadb >=0.4.24
Requires-Dist: sentence-transformers >=2.6.1
Requires-Dist: nltk >=3.8.1
Requires-Dist: unstructured[pdf] ==0.13.0
Requires-Dist: unstructured-client >=0.18.0
Requires-Dist: openai >=1.10.0
